zahner_potentiostat/__init__.py
zahner_potentiostat/display/__init__.py
zahner_potentiostat/display/dcplot.py
zahner_potentiostat/display/onlinedisplay.py
zahner_potentiostat/drivecycle/HUDDSCOL.py
zahner_potentiostat/drivecycle/NYCCCOL.py
zahner_potentiostat/drivecycle/__init__.py
zahner_potentiostat/drivecycle/cycle_importer.py
zahner_potentiostat/drivecycle/sources.txt
zahner_potentiostat/scpi_control/__init__.py
zahner_potentiostat/scpi_control/control.py
zahner_potentiostat/scpi_control/datahandler.py
zahner_potentiostat/scpi_control/datareceiver.py
zahner_potentiostat/scpi_control/error.py
zahner_potentiostat/scpi_control/searcher.py
zahner_potentiostat/scpi_control/serial_interface.py
zahner_potentiostat-1.1.2.dist-info/licenses/LICENSE
zahner_potentiostat-1.1.2.dist-info/METADATA
zahner_potentiostat-1.1.2.dist-info/WHEEL
zahner_potentiostat-1.1.2.dist-info/top_level.txt
zahner_potentiostat-1.1.2.dist-info/RECORD
